solo/__init__.py
solo/args/__init__.py
solo/args/dataset.py
solo/args/setup.py
solo/args/utils.py
solo/losses/__init__.py
solo/losses/barlow.py
solo/losses/byol.py
solo/losses/deepclusterv2.py
solo/losses/dino.py
solo/losses/moco.py
solo/losses/nnclr.py
solo/losses/ressl.py
solo/losses/simclr.py
solo/losses/simsiam.py
solo/losses/swav.py
solo/losses/vicreg.py
solo/losses/wmse.py
solo/methods/__init__.py
solo/methods/barlow_twins.py
solo/methods/base.py
solo/methods/byol.py
solo/methods/dali.py
solo/methods/deepclusterv2.py
solo/methods/dino.py
solo/methods/linear.py
solo/methods/mocov2plus.py
solo/methods/nnbyol.py
solo/methods/nnclr.py
solo/methods/nnsiam.py
solo/methods/ressl.py
solo/methods/simclr.py
solo/methods/simsiam.py
solo/methods/swav.py
solo/methods/vicreg.py
solo/methods/wmse.py
solo/utils/__init__.py
solo/utils/auto_resumer.py
solo/utils/auto_umap.py
solo/utils/backbones.py
solo/utils/checkpointer.py
solo/utils/classification_dataloader.py
solo/utils/dali_dataloader.py
solo/utils/kmeans.py
solo/utils/knn.py
solo/utils/lars.py
solo/utils/metrics.py
solo/utils/misc.py
solo/utils/momentum.py
solo/utils/pretrain_dataloader.py
solo/utils/sinkhorn_knopp.py
solo/utils/whitening.py
tests/__init__.py
tests/args/__init__.py
tests/args/test_datasets.py
tests/args/test_setup.py
tests/dali/__init__.py
tests/dali/test_dali_dataloader.py
tests/dali/test_dali_model.py
tests/dali/utils.py
tests/losses/__init__.py
tests/losses/test_barlow.py
tests/losses/test_byol.py
tests/losses/test_dino.py
tests/losses/test_moco.py
tests/losses/test_nnclr.py
tests/losses/test_ressl.py
tests/losses/test_simclr.py
tests/losses/test_simsiam.py
tests/losses/test_swav.py
tests/losses/test_vicreg.py
tests/losses/test_wmse.py
tests/methods/__init__.py
tests/methods/test_barlow_twins.py
tests/methods/test_base.py
tests/methods/test_byol.py
tests/methods/test_deepclusterv2.py
tests/methods/test_dino.py
tests/methods/test_linear.py
tests/methods/test_mocov2plus.py
tests/methods/test_nnbyol.py
solo_learn-1.0.2.dist-info/LICENSE
solo_learn-1.0.2.dist-info/METADATA
solo_learn-1.0.2.dist-info/WHEEL
solo_learn-1.0.2.dist-info/dependency_links.txt
solo_learn-1.0.2.dist-info/top_level.txt
solo_learn-1.0.2.dist-info/RECORD
